.svnignore
README.txt
setup.cfg
setup.py
docs/HISTORY.txt
docs/INSTALL.txt
docs/LICENSE.GPL
docs/LICENSE.txt
slc/__init__.py
slc.aggregation.egg-info/PKG-INFO
slc.aggregation.egg-info/SOURCES.txt
slc.aggregation.egg-info/dependency_links.txt
slc.aggregation.egg-info/entry_points.txt
slc.aggregation.egg-info/namespace_packages.txt
slc.aggregation.egg-info/not-zip-safe
slc.aggregation.egg-info/paster_plugins.txt
slc.aggregation.egg-info/requires.txt
slc.aggregation.egg-info/top_level.txt
slc/aggregation/__init__.py
slc/aggregation/config.py
slc/aggregation/configure.zcml
slc/aggregation/descriptors.py
slc/aggregation/interfaces.py
slc/aggregation/setuphandlers.py
slc/aggregation/browser/__init__.py
slc/aggregation/browser/aggregator.py
slc/aggregation/browser/configure.zcml
slc/aggregation/browser/interfaces.py
slc/aggregation/browser/templates/aggregator.pt
slc/aggregation/profiles/default/actions.xml
slc/aggregation/profiles/default/metadata.xml
slc/aggregation/profiles/default/slc_zentralise_marker.txt
slc/aggregation/tests/__init__.py
slc/aggregation/tests/base.py
slc/aggregation/tests/test_aggregator.py