Metadata-Version: 1.0
Name: slc.aggregation
Version: 1.2
Summary: Provides an aggregation solution aimed at Plone sites with many different language versions
Home-page: http://plone.org/products/slc.aggregation
Author: JC Brand, Syslab.com GmbH
Author-email: brand@syslab.com
License: GPL
Keywords: syslab plone resource centralisation
Platform: UNKNOWN
Classifier: Framework :: Plone
Classifier: Programming Language :: Python
Classifier: Topic :: Software Development :: Libraries :: Python Modules
